orange_toast_mcp_server-0.1.0.dist-info/licenses/LICENSE
src/__init__.py
src/mcp/__init__.py
src/mcp/protocol.py
src/mcp/validation.py
src/notification/__init__.py
src/notification/macos.py
src/notification/manager.py
src/notification/platform.py
src/notification/toast.py
src/server/__init__.py
src/server/commands.py
src/server/connection.py
tests/__init__.py
tests/test_commands.py
tests/test_connection.py
tests/test_macos.py
tests/test_manager.py
tests/test_protocol.py
tests/test_toast.py
orange_toast_mcp_server-0.1.0.dist-info/METADATA
orange_toast_mcp_server-0.1.0.dist-info/WHEEL
orange_toast_mcp_server-0.1.0.dist-info/top_level.txt
orange_toast_mcp_server-0.1.0.dist-info/RECORD
