Metadata-Version: 2.4
Name: orange-toast-mcp-server
Version: 0.1.0
Summary: A Model Context Protocol (MCP) server with Windows 10 and macOS desktop notifications support
License: MIT
Requires-Python: >=3.8
License-File: LICENSE
Requires-Dist: win10toast; platform_system == "Windows"
Dynamic: license-file
Dynamic: requires-python
